basic_ui/__init__.py
basic_ui/main.py
basic_ui/config/aliases.json
basic_ui/config/defaults.json
basic_ui/config/requirements.json
basic_ui-0.4.8.dist-info/LICENSE
basic_ui-0.4.8.dist-info/METADATA
basic_ui-0.4.8.dist-info/WHEEL
basic_ui-0.4.8.dist-info/top_level.txt
basic_ui-0.4.8.dist-info/RECORD
