Metadata-Version: 2.1
Name: basic_ui
Version: 0.4.8
Summary: basic ui is a package for pygame to create interfaces easly based on json files
Author: Legregz
License-File: LICENSE
